tinyPeriodicTask/IntervalSettings.py
tinyPeriodicTask/IntervalUnitEnum.py
tinyPeriodicTask/SettingsTypeEnum.py
tinyPeriodicTask/StartAtSettings.py
tinyPeriodicTask/TinyPeriodicTask.py
tinyPeriodicTask/__init__.py
tinyPeriodicTask/packageInfo.py
tinyPeriodicTask-1.4.5.dist-info/METADATA
tinyPeriodicTask-1.4.5.dist-info/RECORD
tinyPeriodicTask-1.4.5.dist-info/WHEEL
tinyPeriodicTask-1.4.5.dist-info/top_level.txt
