Metadata-Version: 2.1
Name: tinyPeriodicTask
Version: 1.4.5
Summary: Simple periodic execution of a function.
Home-page: https://github.com/fredericklussier/TinyPeriodicTask
Author: Frederick Lussier
Author-email: frederick.lussier@hotmail.com
License: MIT
Download-URL: https://github.com/fredericklussier/TinyPeriodicTask/tree/1.4.5
Keywords: periodic,jobs,job scheduler,job scheduling
Platform: UNKNOWN
Classifier: Development Status :: 4 - Beta
Classifier: Intended Audience :: Developers
Classifier: License :: OSI Approved :: MIT License
Classifier: Programming Language :: Python :: 3.5
Classifier: Programming Language :: Python :: 3.6
Classifier: Natural Language :: English
